{
    "c4095926-578e-4090-901f-5f8d4f9bb8e5": [
        {
            "code_content": "#include <bits/stdc++.h>\nusing namespace std;\n\nclass solution {\npublic:\n    long long subarrayProductBelowK(vector<int>& arr, int k) {\n        //Write your code here...\n        \n        \n    }  \n\n};",
            "language": "CPP"
        },
        {
            "code_content": "class solution:\n    def subarrayProductBelowK(self, arr, k):\n        #Write your code here...\n        pass",
            "language": "PYTHON"
        },
        {
            "code_content": "import java.util.*;\n\npublic class Solution {\n    public static long subarrayProductBelowK(int[] arr, int k) {\n        //Write your code here...\n        \n        \n    }\n\n}",
            "language": "JAVA"
        }
    ],
    "38503060-8a1c-4bd0-a23b-984a4def86d2": [
        {
            "code_content": "#include <bits/stdc++.h>\nusing namespace std;\n\nclass solution {\npublic:\n    long long subarrayProductBelowK(vector<int>& arr, int k) {\n        if (k <= 1) {\n            return 0;\n        }\n        long long product = 1;\n        long long count = 0;\n        int left = 0;\n\n        for (int right = 0; right < (int)arr.size(); right++) {\n            product *= arr[right];\n            while (product >= k) {\n                product /= arr[left];\n                left++;\n            }\n            count += right - left + 1;\n        }\n\n        return count;\n    }\n};",
            "language": "CPP"
        },
        {
            "code_content": "import java.util.*;\n\nclass Solution {\n    public static long subarrayProductBelowK(int[] arr, int k) {\n        if (k <= 1) return 0;\n        long product = 1;\n        int left = 0;\n        long count = 0;\n        for (int right = 0; right < arr.length; right++) {\n            product *= arr[right];\n            while (product >= k) {\n                product /= arr[left];\n                left++;\n            }\n            count += right - left + 1;\n        }\n        return count;\n    }\n}",
            "language": "JAVA"
        },
        {
            "code_content": "class solution:\n    def subarrayProductBelowK(self, arr, k):\n        if k <= 1:\n            return 0\n        \n        product = 1\n        count = 0\n        left = 0\n        \n        for right in range(len(arr)):\n            product *= arr[right]\n            while product >= k:\n                product /= arr[left]\n                left += 1\n            count += right - left + 1\n        \n        return count",
            "language": "PYTHON"
        }
    ]
}